{
	"comment":"Based on https://docs.oracle.com/javase/tutorial/java/nutsandbolts/opsummary.html",
	"string-delineators":["\"","'"],
	"single-line-comment-opener":"//",
	"multi-line-comment-opener":"/*",
	"multi-line-comment-closer":"*/",
	"multiples":[
		"==",
		"!=",
		">=",
		"<=",
		"&&",
		"||",
		"%=",
		"/=",
		"+=",
		"-=",
		"*=",
		"++",
		"--",
		"[]",
		"{}",
		"<<",
		">>",
		">>>"
	],
	"splitters":"\t\n\r ",
	"keepers":"`¬!\"£$%^&*()-+=[]{};'#:@~,/<>?\\|",
	"labels":{
		"operator":[
			"=",
			"+",
			"-",
			"*",
			"/",
			"%",
			"+",
			"-",
			"++",
			"--",
			"!",
			"==",
			"!=",
			">",
			">=",
			"<",
			"<=",
			"&&",
			"||",
			"?",
			":",
			"instanceof",
			"~",
			"<<",
			">>",
			">>>",
			"&",
			"^",
			"|"
		],
		"delineator":["{","}","(",")","[","]"],
		"terminator":[";"],
		"keyword":[
			"return",
			"if",
			"else",
			"while",
			"for",
			"do",
			"switch",
			"case",
			"break",
			"try",
			"catch",
			"finally",
			"throw",
			"throws",
			"class",
			"interface",
			"abstract",
			"static",
			"final",
			"public",
			"private",
			"protected",
			"extends",
			"implements"
		]
	}
}
